{
  "doc_id": "synthetic_10",
  "topic": "overexertion",
  "type": "faq",
  "title": "Overexertion - Faq",
  "content": "## Frequently Asked Questions about overexertion\n\n**Q: What are the main symptoms?**\nA: Common symptoms include...\n\n**Q: How is it diagnosed?**\nA: Diagnosis typically involves...\n\n### Key Management Strategies\n\nRegular follow-up with healthcare providers is essential for optimal management.\n\n### Important Considerations\n\n- Always consult with your healthcare provider before making changes to your treatment plan\n- Individual responses to treatments may vary\n- Regular monitoring and follow-up are crucial\n\n*This is educational content and not a substitute for professional medical advice.*",
  "source": "synthetic_mock",
  "generated_at": "2026-01-07T20:03:09.346679",
  "metadata": {
    "model": "mock_generator",
    "word_count": 82
  }
}